odoo/addons/quality_control_wait_approval/README.rst
odoo/addons/quality_control_wait_approval/__init__.py
odoo/addons/quality_control_wait_approval/__manifest__.py
odoo/addons/quality_control_wait_approval/models/__init__.py
odoo/addons/quality_control_wait_approval/models/qc_inspection.py
odoo/addons/quality_control_wait_approval/readme/CONTRIBUTORS.md
odoo/addons/quality_control_wait_approval/readme/DESCRIPTION.md
odoo/addons/quality_control_wait_approval/readme/USAGE.md
odoo/addons/quality_control_wait_approval/static/description/icon.png
odoo/addons/quality_control_wait_approval/static/description/index.html
odoo/addons/quality_control_wait_approval/tests/__init__.py
odoo/addons/quality_control_wait_approval/tests/test_quality_control_wait_approval.py
odoo_addon_quality_control_wait_approval-17.0.1.0.0.1.dist-info/METADATA
odoo_addon_quality_control_wait_approval-17.0.1.0.0.1.dist-info/WHEEL
odoo_addon_quality_control_wait_approval-17.0.1.0.0.1.dist-info/top_level.txt
odoo_addon_quality_control_wait_approval-17.0.1.0.0.1.dist-info/RECORD
