Metadata-Version: 2.1
Name: odoo-addon-quality_control_wait_approval
Version: 17.0.1.0.0.1
Requires-Python: >=3.10
Requires-Dist: odoo-addon-quality_control_oca>=17.0dev,<17.1dev
Requires-Dist: odoo>=17.0a,<17.1dev
Summary: Always pass through the 'Waiting supervisor approval' in Inspections
Home-page: https://github.com/sygel-technology/sy-manufacture
License: AGPL-3
Author: Sygel, Odoo Community Association (OCA)
Author-email: support@odoo-community.org
Classifier: Programming Language :: Python
Classifier: Framework :: Odoo
Classifier: Framework :: Odoo :: 17.0
Classifier: License :: OSI Approved :: GNU Affero General Public License v3
